cybercure/__init__.py
cybercure-0.4.3.dist-info/METADATA
cybercure-0.4.3.dist-info/RECORD
cybercure-0.4.3.dist-info/WHEEL
cybercure-0.4.3.dist-info/top_level.txt
