Metadata-Version: 2.1
Name: cybercure
Version: 0.4.3
Summary: Python SDK to integrate cybercure.ai cyber intel feeds quickly and easily
Home-page: https://github.com/grispan56/CyberCure.ai-Python-sdk
Author: CyberCure.ai
Author-email: author@example.com
License: MIT
Platform: UNKNOWN
Classifier: Programming Language :: Python :: 3
Classifier: License :: OSI Approved :: MIT License
Classifier: Operating System :: OS Independent
